chainzpy/__init__.py
chainzpy/main.py
chainzpy-0.7.dist-info/METADATA
chainzpy-0.7.dist-info/WHEEL
chainzpy-0.7.dist-info/top_level.txt
chainzpy-0.7.dist-info/RECORD
