Metadata-Version: 2.1
Name: chainzpy
Version: 0.7
Summary: API wrapper for https://chainz.cryptoid.info/
Requires-Dist: requests
Requires-Dist: bs4
